{
  "test": {
    "configuration": {
      "testId": "PYZW15D200T15R0",
      "task": "ReciprocalTappingTest",
      "numberOfTargets": 15,
      "targetWidth": 0.015,
      "targetDistance": 0.2,
      "indexOfDifficulty": 3.84130239,
      "numOfBlocksPerTest": 1,
      "targetsPositions": [
        {
          "x": 0.15,
          "y": -0.24999997,
          "z": 0.349999964
        },
        {
          "x": 0.129208833,
          "y": -0.447814763,
          "z": 0.350000024
        },
        {
          "x": 0.190673679,
          "y": -0.258645445,
          "z": 0.35
        },
        {
          "x": 0.09122147,
          "y": -0.4309017,
          "z": 0.35
        },
        {
          "x": 0.2243145,
          "y": -0.283086926,
          "z": 0.35
        },
        {
          "x": 0.06339746,
          "y": -0.4,
          "z": 0.35
        },
        {
          "x": 0.245105654,
          "y": -0.3190983,
          "z": 0.35
        },
        {
          "x": 0.0505478159,
          "y": -0.360452831,
          "z": 0.35
        },
        {
          "x": 0.2494522,
          "y": -0.360452831,
          "z": 0.35
        },
        {
          "x": 0.0548943579,
          "y": -0.319098264,
          "z": 0.35
        },
        {
          "x": 0.236602545,
          "y": -0.4,
          "z": 0.35
        },
        {
          "x": 0.07568553,
          "y": -0.2830869,
          "z": 0.35
        },
        {
          "x": 0.20877853,
          "y": -0.4309017,
          "z": 0.35
        },
        {
          "x": 0.109326355,
          "y": -0.258645415,
          "z": 0.35
        },
        {
          "x": 0.170791164,
          "y": -0.447814763,
          "z": 0.350000024
        }
      ]
    },
    "data": {
      "timestamp": "2019-05-27T21:28:39",
      "testId": "PYZW15D200T15R0",
      "planeOrientation": "YZ",
      "initialTime": 456.117035,
      "finalTime": 465.65448,
      "testDuration": 9.537445,
      "blocksData": [
        {
          "blockId": 0,
          "initialTargetId": 0,
          "initialTime": 456.117035,
          "finalTime": 465.65448,
          "blockDuration": 9.537445,
          "trialsData": [
            {
              "trialId": 0,
              "initialTargetId": 0,
              "finalTargetId": 8,
              "initialTime": 456.117065,
              "finalTime": 456.7756,
              "trialDuration": 0.6585388,
              "initialPosition": {
                "x": 0.15,
                "y": -0.2530651,
                "z": 0.35
              },
              "finalPosition": {
                "x": 0.130842924,
                "y": -0.45,
                "z": 0.35
              },
              "missedTarget": false,
              "finalProjectedCoordinate": 0.00200244738
            },
            {
              "trialId": 1,
              "initialTargetId": 8,
              "finalTargetId": 1,
              "initialTime": 456.775635,
              "finalTime": 457.376068,
              "trialDuration": 0.60043335,
              "initialPosition": {
                "x": 0.130842924,
                "y": -0.45,
                "z": 0.35
              },
              "finalPosition": {
                "x": 0.19367817,
                "y": -0.256130248,
                "z": 0.35
              },
              "missedTarget": false,
              "finalProjectedCoordinate": 0.00332053332
            },
            {
              "trialId": 2,
              "initialTargetId": 1,
              "finalTargetId": 9,
              "initialTime": 457.376129,
              "finalTime": 457.916,
              "trialDuration": 0.539855957,
              "initialPosition": {
                "x": 0.19367817,
                "y": -0.256130248,
                "z": 0.35
              },
              "finalPosition": {
                "x": 0.0963601544,
                "y": -0.436206877,
                "z": 0.35
              },
              "missedTarget": false,
              "finalProjectedCoordinate": 0.00202505733
            },
            {
              "trialId": 3,
              "initialTargetId": 9,
              "finalTargetId": 2,
              "initialTime": 457.916016,
              "finalTime": 458.489838,
              "trialDuration": 0.573822,
              "initialPosition": {
                "x": 0.0963601544,
                "y": -0.436206877,
                "z": 0.35
              },
              "finalPosition": {
                "x": 0.231226057,
                "y": -0.2814176,
                "z": 0.35
              },
              "missedTarget": false,
              "finalProjectedCoordinate": 0.00586527772
            },
            {
              "trialId": 4,
              "initialTargetId": 2,
              "finalTargetId": 10,
              "initialTime": 458.4899,
              "finalTime": 459.253632,
              "trialDuration": 0.7637329,
              "initialPosition": {
                "x": 0.231226057,
                "y": -0.2814176,
                "z": 0.35
              },
              "finalPosition": {
                "x": 0.0672413856,
                "y": -0.397126436,
                "z": 0.35
              },
              "missedTarget": false,
              "finalProjectedCoordinate": -0.004798856
            },
            {
              "trialId": 5,
              "initialTargetId": 10,
              "finalTargetId": 3,
              "initialTime": 459.2537,
              "finalTime": 459.905548,
              "trialDuration": 0.651855469,
              "initialPosition": {
                "x": 0.0672413856,
                "y": -0.397126436,
                "z": 0.35
              },
              "finalPosition": {
                "x": 0.249616861,
                "y": -0.322030634,
                "z": 0.35
              },
              "missedTarget": false,
              "finalProjectedCoordinate": 0.002928511
            },
            {
              "trialId": 6,
              "initialTargetId": 3,
              "finalTargetId": 11,
              "initialTime": 459.905579,
              "finalTime": 460.518646,
              "trialDuration": 0.6130676,
              "initialPosition": {
                "x": 0.249616861,
                "y": -0.322030634,
                "z": 0.35
              },
              "finalPosition": {
                "x": 0.0480842963,
                "y": -0.360344827,
                "z": 0.35
              },
              "missedTarget": false,
              "finalProjectedCoordinate": 0.00238724286
            },
            {
              "trialId": 7,
              "initialTargetId": 11,
              "finalTargetId": 4,
              "initialTime": 460.518677,
              "finalTime": 461.089478,
              "trialDuration": 0.5708008,
              "initialPosition": {
                "x": 0.0480842963,
                "y": -0.360344827,
                "z": 0.35
              },
              "finalPosition": {
                "x": 0.2572797,
                "y": -0.361877382,
                "z": 0.35
              },
              "missedTarget": false,
              "finalProjectedCoordinate": 0.007827497
            },
            {
              "trialId": 8,
              "initialTargetId": 4,
              "finalTargetId": 12,
              "initialTime": 461.089539,
              "finalTime": 461.654541,
              "trialDuration": 0.565002441,
              "initialPosition": {
                "x": 0.2572797,
                "y": -0.361877382,
                "z": 0.35
              },
              "finalPosition": {
                "x": 0.0496168658,
                "y": -0.31743294,
                "z": 0.35
              },
              "missedTarget": false,
              "finalProjectedCoordinate": 0.005508401
            },
            {
              "trialId": 9,
              "initialTargetId": 12,
              "finalTargetId": 5,
              "initialTime": 461.6546,
              "finalTime": 462.319183,
              "trialDuration": 0.6645813,
              "initialPosition": {
                "x": 0.0496168658,
                "y": -0.31743294,
                "z": 0.35
              },
              "finalPosition": {
                "x": 0.241954029,
                "y": -0.3978927,
                "z": 0.35
              },
              "missedTarget": false,
              "finalProjectedCoordinate": 0.004031706
            },
            {
              "trialId": 10,
              "initialTargetId": 5,
              "finalTargetId": 13,
              "initialTime": 462.319244,
              "finalTime": 463.041046,
              "trialDuration": 0.721801758,
              "initialPosition": {
                "x": 0.241954029,
                "y": -0.3978927,
                "z": 0.35
              },
              "finalPosition": {
                "x": 0.08103449,
                "y": -0.28371647,
                "z": 0.35
              },
              "missedTarget": false,
              "finalProjectedCoordinate": -0.00469742529
            },
            {
              "trialId": 11,
              "initialTargetId": 13,
              "finalTargetId": 6,
              "initialTime": 463.041077,
              "finalTime": 463.6957,
              "trialDuration": 0.654632568,
              "initialPosition": {
                "x": 0.08103449,
                "y": -0.28371647,
                "z": 0.35
              },
              "finalPosition": {
                "x": 0.204406142,
                "y": -0.431609184,
                "z": 0.35
              },
              "missedTarget": false,
              "finalProjectedCoordinate": -0.002399947
            },
            {
              "trialId": 12,
              "initialTargetId": 6,
              "finalTargetId": 14,
              "initialTime": 463.69574,
              "finalTime": 464.279877,
              "trialDuration": 0.584136963,
              "initialPosition": {
                "x": 0.204406142,
                "y": -0.431609184,
                "z": 0.35
              },
              "finalPosition": {
                "x": 0.108620696,
                "y": -0.2591954,
                "z": 0.35
              },
              "missedTarget": false,
              "finalProjectedCoordinate": -0.000123450533
            },
            {
              "trialId": 13,
              "initialTargetId": 14,
              "finalTargetId": 7,
              "initialTime": 464.279938,
              "finalTime": 464.8841,
              "trialDuration": 0.6041565,
              "initialPosition": {
                "x": 0.108620696,
                "y": -0.2591954,
                "z": 0.35
              },
              "finalPosition": {
                "x": 0.165325671,
                "y": -0.4599617,
                "z": 0.35
              },
              "missedTarget": true,
              "finalProjectedCoordinate": 0.009863514
            },
            {
              "trialId": 14,
              "initialTargetId": 7,
              "finalTargetId": 0,
              "initialTime": 464.884125,
              "finalTime": 465.654419,
              "trialDuration": 0.7702942,
              "initialPosition": {
                "x": 0.165325671,
                "y": -0.4599617,
                "z": 0.35
              },
              "finalPosition": {
                "x": 0.14616859,
                "y": -0.2591954,
                "z": 0.35
              },
              "missedTarget": false,
              "finalProjectedCoordinate": -0.00874454
            }
          ]
        }
      ]
    }
  },
  "computedResults": {
    "totalTrials": 15,
    "totalMissedTargets": 1,
    "totalMovementTime": 9.536713,
    "errorRate": 0.06666667,
    "averageMovementTime": 0.6357809,
    "effectiveWidth": 0.0209188741,
    "effectiveIndexOfDifficulty": 3.40063953,
    "throughput": 5.3487606
  },
  "participantName": "MouseOnScreen",
  "participantAge": 27,
  "testDescription": "Preliminar test for mouse learning curve",
  "testTask": "ReciprocalTappingTest",
  "device": "Mouse",
  "interactionTechnique": "Mouse_LeftButton",
  "cursorDiameter": 0.01,
  "planeOrientation": "YZ"
}