{
  "test": {
    "configuration": {
      "testId": "PYZW35D200T9R0",
      "task": "ReciprocalTappingTest",
      "numberOfTargets": 9,
      "targetWidth": 0.035,
      "targetDistance": 0.2,
      "indexOfDifficulty": 2.74723387,
      "numOfBlocksPerTest": 2,
      "targetsPositions": [
        {
          "x": 0.15,
          "y": -0.24999997,
          "z": 0.45
        },
        {
          "x": 0.115797967,
          "y": -0.44396925,
          "z": 0.45
        },
        {
          "x": 0.214278772,
          "y": -0.273395538,
          "z": 0.45
        },
        {
          "x": 0.06339746,
          "y": -0.4,
          "z": 0.45
        },
        {
          "x": 0.2484808,
          "y": -0.3326352,
          "z": 0.45
        },
        {
          "x": 0.0515192375,
          "y": -0.332635134,
          "z": 0.45
        },
        {
          "x": 0.236602545,
          "y": -0.4,
          "z": 0.45
        },
        {
          "x": 0.08572126,
          "y": -0.273395538,
          "z": 0.45
        },
        {
          "x": 0.184202015,
          "y": -0.44396928,
          "z": 0.45
        }
      ]
    },
    "data": {
      "timestamp": "2019-05-23T19:52:58",
      "testId": "PYZW35D200T9R0",
      "planeOrientation": "YZ",
      "initialTime": 34.8482666,
      "finalTime": 58.9207573,
      "testDuration": 24.07249,
      "blocksData": [
        {
          "blockId": 0,
          "initialTargetId": 0,
          "initialTime": 34.8488846,
          "finalTime": 50.3790474,
          "blockDuration": 15.5301628,
          "trialsData": [
            {
              "trialId": 0,
              "initialTargetId": 0,
              "finalTargetId": 5,
              "initialTime": 34.849556,
              "finalTime": 41.40679,
              "trialDuration": 6.55723572,
              "initialPosition": {
                "x": 0.148591638,
                "y": -0.249326587,
                "z": 0.4531591
              },
              "finalPosition": {
                "x": 0.115829378,
                "y": -0.461171716,
                "z": 0.464281768
              },
              "missedTarget": false,
              "finalProjectedCoordinate": 0.0169356465
            },
            {
              "trialId": 1,
              "initialTargetId": 5,
              "finalTargetId": 1,
              "initialTime": 41.7149353,
              "finalTime": 42.36591,
              "trialDuration": 0.6509743,
              "initialPosition": {
                "x": 0.115454286,
                "y": -0.445497245,
                "z": 0.454344124
              },
              "finalPosition": {
                "x": 0.198270187,
                "y": -0.278471768,
                "z": 0.438707829
              },
              "missedTarget": false,
              "finalProjectedCoordinate": -0.0124004632
            },
            {
              "trialId": 2,
              "initialTargetId": 1,
              "finalTargetId": 6,
              "initialTime": 42.67145,
              "finalTime": 43.44923,
              "trialDuration": 0.7777786,
              "initialPosition": {
                "x": 0.213081092,
                "y": -0.2813638,
                "z": 0.465810776
              },
              "finalPosition": {
                "x": 0.0635639355,
                "y": -0.4187273,
                "z": 0.460216373
              },
              "missedTarget": false,
              "finalProjectedCoordinate": 0.0119101554
            },
            {
              "trialId": 3,
              "initialTargetId": 6,
              "finalTargetId": 2,
              "initialTime": 43.7550545,
              "finalTime": 44.7674637,
              "trialDuration": 1.01240921,
              "initialPosition": {
                "x": 0.0626566038,
                "y": -0.409695446,
                "z": 0.453394115
              },
              "finalPosition": {
                "x": 0.2557302,
                "y": -0.342729449,
                "z": 0.46796298
              },
              "missedTarget": false,
              "finalProjectedCoordinate": 0.00335976481
            },
            {
              "trialId": 4,
              "initialTargetId": 2,
              "finalTargetId": 7,
              "initialTime": 45.074604,
              "finalTime": 45.9210968,
              "trialDuration": 0.846492767,
              "initialPosition": {
                "x": 0.245527446,
                "y": -0.34015888,
                "z": 0.4632006
              },
              "finalPosition": {
                "x": 0.0310655832,
                "y": -0.3292608,
                "z": 0.4437613
              },
              "missedTarget": false,
              "finalProjectedCoordinate": 0.0204536617
            },
            {
              "trialId": 5,
              "initialTargetId": 7,
              "finalTargetId": 3,
              "initialTime": 46.22781,
              "finalTime": 47.12949,
              "trialDuration": 0.90168,
              "initialPosition": {
                "x": 0.0416622236,
                "y": -0.33539477,
                "z": 0.4452031
              },
              "finalPosition": {
                "x": 0.240086183,
                "y": -0.418332875,
                "z": 0.456940085
              },
              "missedTarget": false,
              "finalProjectedCoordinate": 0.00954377651
            },
            {
              "trialId": 6,
              "initialTargetId": 3,
              "finalTargetId": 8,
              "initialTime": 47.43488,
              "finalTime": 48.00377,
              "trialDuration": 0.5688896,
              "initialPosition": {
                "x": 0.236619756,
                "y": -0.397766262,
                "z": 0.455913246
              },
              "finalPosition": {
                "x": 0.105874717,
                "y": -0.276400149,
                "z": 0.442263782
              },
              "missedTarget": false,
              "finalProjectedCoordinate": -0.0173697621
            },
            {
              "trialId": 7,
              "initialTargetId": 8,
              "finalTargetId": 4,
              "initialTime": 48.31086,
              "finalTime": 49.1853561,
              "trialDuration": 0.87449646,
              "initialPosition": {
                "x": 0.07880324,
                "y": -0.256815523,
                "z": 0.447582543
              },
              "finalPosition": {
                "x": 0.181163371,
                "y": -0.459651351,
                "z": 0.464436978
              },
              "missedTarget": false,
              "finalProjectedCoordinate": 0.0120617449
            },
            {
              "trialId": 8,
              "initialTargetId": 4,
              "finalTargetId": 0,
              "initialTime": 49.4925156,
              "finalTime": 50.07423,
              "trialDuration": 0.58171463,
              "initialPosition": {
                "x": 0.175105944,
                "y": -0.43690604,
                "z": 0.456004232
              },
              "finalPosition": {
                "x": 0.15605773,
                "y": -0.266440868,
                "z": 0.4416405
              },
              "missedTarget": false,
              "finalProjectedCoordinate": -0.0172430277
            }
          ]
        },
        {
          "blockId": 1,
          "initialTargetId": 0,
          "initialTime": 50.3792534,
          "finalTime": 58.9205971,
          "blockDuration": 8.541344,
          "trialsData": [
            {
              "trialId": 0,
              "initialTargetId": 0,
              "finalTargetId": 5,
              "initialTime": 50.3792648,
              "finalTime": 51.2689934,
              "trialDuration": 0.889728546,
              "initialPosition": {
                "x": 0.154854774,
                "y": -0.245973423,
                "z": 0.4504624
              },
              "finalPosition": {
                "x": 0.117278129,
                "y": -0.464613676,
                "z": 0.457087338
              },
              "missedTarget": false,
              "finalProjectedCoordinate": 0.0200737566
            },
            {
              "trialId": 1,
              "initialTargetId": 5,
              "finalTargetId": 1,
              "initialTime": 51.57571,
              "finalTime": 52.1581879,
              "trialDuration": 0.58247757,
              "initialPosition": {
                "x": 0.116535112,
                "y": -0.444854021,
                "z": 0.447134882
              },
              "finalPosition": {
                "x": 0.2005543,
                "y": -0.283744931,
                "z": 0.441250235
              },
              "missedTarget": false,
              "finalProjectedCoordinate": -0.0158250779
            },
            {
              "trialId": 2,
              "initialTargetId": 1,
              "finalTargetId": 6,
              "initialTime": 52.463,
              "finalTime": 53.1155968,
              "trialDuration": 0.6525955,
              "initialPosition": {
                "x": 0.2220521,
                "y": -0.2768923,
                "z": 0.444529235
              },
              "finalPosition": {
                "x": 0.08056963,
                "y": -0.394964,
                "z": 0.447048336
              },
              "missedTarget": false,
              "finalProjectedCoordinate": -0.0163917542
            },
            {
              "trialId": 3,
              "initialTargetId": 6,
              "finalTargetId": 2,
              "initialTime": 53.4218025,
              "finalTime": 54.0188179,
              "trialDuration": 0.5970154,
              "initialPosition": {
                "x": 0.057523787,
                "y": -0.398994744,
                "z": 0.446818948
              },
              "finalPosition": {
                "x": 0.22695902,
                "y": -0.336387277,
                "z": 0.450975
              },
              "missedTarget": false,
              "finalProjectedCoordinate": -0.0215071589
            },
            {
              "trialId": 4,
              "initialTargetId": 2,
              "finalTargetId": 7,
              "initialTime": 54.32574,
              "finalTime": 54.9917526,
              "trialDuration": 0.6660118,
              "initialPosition": {
                "x": 0.2477552,
                "y": -0.327458352,
                "z": 0.451735944
              },
              "finalPosition": {
                "x": 0.0699622,
                "y": -0.3237627,
                "z": 0.451199263
              },
              "missedTarget": false,
              "finalProjectedCoordinate": -0.0184429586
            },
            {
              "trialId": 5,
              "initialTargetId": 7,
              "finalTargetId": 3,
              "initialTime": 55.2987251,
              "finalTime": 55.9617348,
              "trialDuration": 0.663009644,
              "initialPosition": {
                "x": 0.04676281,
                "y": -0.3349,
                "z": 0.4563371
              },
              "finalPosition": {
                "x": 0.219205827,
                "y": -0.399283946,
                "z": 0.4624121
              },
              "missedTarget": false,
              "finalProjectedCoordinate": -0.0165924728
            },
            {
              "trialId": 6,
              "initialTargetId": 3,
              "finalTargetId": 8,
              "initialTime": 56.26822,
              "finalTime": 56.86573,
              "trialDuration": 0.5975113,
              "initialPosition": {
                "x": 0.242450878,
                "y": -0.412017822,
                "z": 0.457683921
              },
              "finalPosition": {
                "x": 0.101432711,
                "y": -0.279172122,
                "z": 0.443572581
              },
              "missedTarget": false,
              "finalProjectedCoordinate": -0.0157487839
            },
            {
              "trialId": 7,
              "initialTargetId": 8,
              "finalTargetId": 4,
              "initialTime": 57.17176,
              "finalTime": 57.7683868,
              "trialDuration": 0.5966263,
              "initialPosition": {
                "x": 0.07722894,
                "y": -0.262706935,
                "z": 0.4520458
              },
              "finalPosition": {
                "x": 0.182112113,
                "y": -0.427051485,
                "z": 0.460258842
              },
              "missedTarget": false,
              "finalProjectedCoordinate": -0.0156962126
            },
            {
              "trialId": 8,
              "initialTargetId": 4,
              "finalTargetId": 0,
              "initialTime": 58.0745049,
              "finalTime": 58.6153831,
              "trialDuration": 0.5408783,
              "initialPosition": {
                "x": 0.1818666,
                "y": -0.437342346,
                "z": 0.46134764
              },
              "finalPosition": {
                "x": 0.151584968,
                "y": -0.2675476,
                "z": 0.438398421
              },
              "missedTarget": false,
              "finalProjectedCoordinate": -0.01755628
            }
          ]
        }
      ]
    }
  },
  "computedResults": {
    "totalTrials": 18,
    "totalMissedTargets": 0,
    "totalMovementTime": 18.5575256,
    "errorRate": 0,
    "averageMovementTime": 1.03097367,
    "effectiveWidth": 0.06493215,
    "effectiveIndexOfDifficulty": 2.028618,
    "throughput": 1.96767211
  },
  "participantName": "John2",
  "participantAge": 29,
  "testDescription": "Preliminar tests with Dwell",
  "testTask": "ReciprocalTappingTest",
  "device": "LeapMotionController",
  "interactionTechnique": "DwellTime_300ms",
  "cursorDiameter": 0.01,
  "planeOrientation": "YZ"
}